{"namespace":"FlyFreeUrbanDesignSystem_019dd7","components":[{"name":"Footer","sourcePath":"ui_kits/ecommerce/Footer.jsx"},{"name":"Header","sourcePath":"ui_kits/ecommerce/Header.jsx"},{"name":"Hero","sourcePath":"ui_kits/ecommerce/Hero.jsx"},{"name":"ProductCard","sourcePath":"ui_kits/ecommerce/ProductCard.jsx"}],"startingPoints":[],"cards":[{"path":"preview/graphic-elements.html","group":"Brand","viewport":"700x120","subtitle":">> chevron · hazard stripes · yellow/black label bars · left accent","name":"Graphic Elements"},{"path":"preview/icons-persuasive.html","group":"Brand","viewport":"700x160","subtitle":"12 on-brand geometric icons: envíos, seguridad, cuotas, calidad, patín, soporte…","name":"Persuasive Icons"},{"path":"preview/logo-variants.html","group":"Brand","viewport":"700x140","subtitle":"On White (yellow chevrons) · On Black (yellow chevrons) · On Yellow (black chevrons)","name":"Logo Variants"},{"path":"preview/social-post-anatomy.html","group":"Brand","viewport":"700x212","subtitle":"Instagram post templates: yellow full-bleed, left-bar, black","name":"Social Post Anatomy"},{"path":"preview/social-posts-accents.html","group":"Brand","viewport":"760x440","subtitle":"Mismo sistema, 3 familias de acento aplicadas: Electric / Sunset / Outdoor","name":"Social Posts — Accent Families"},{"path":"preview/color-palettes-extended.html","group":"Colors","viewport":"760x900","subtitle":"Amarillo+Negro como ancla + 3 familias de acento (Electric / Sunset / Outdoor)","name":"Extended Accent Palettes"},{"path":"preview/colors-combos.html","group":"Colors","viewport":"700x180","subtitle":"3 authorized pairings: Yellow+Black, Black+Yellow, White+accents","name":"Color Combinations"},{"path":"preview/colors-primary.html","group":"Colors","viewport":"700x180","subtitle":"Amarillo #FFD100 · Negro #231F20 · Blanco #FFFFFF","name":"Primary Color Palette"},{"path":"preview/buttons.html","group":"Components","viewport":"700x200","subtitle":"Primary, dark, outline buttons + tag/badge variants","name":"Buttons & Tags"},{"path":"preview/product-card.html","group":"Components","viewport":"700x200","subtitle":"Ecommerce product card with badge, price, add-to-cart","name":"Product Card"},{"path":"ui_kits/ecommerce/ecommerce-kit.html","group":"Components","viewport":"1280x700","subtitle":"Header · Hero · ProductCard · Footer — FlyFree Urban ecommerce components","name":"Ecommerce UI Kit"},{"path":"preview/shadows-radius.html","group":"Spacing","viewport":"700x140","subtitle":"Flat offset black shadows · minimal radius 0–8px + pill","name":"Shadows & Radius"},{"path":"preview/spacing-tokens.html","group":"Spacing","viewport":"700x130","subtitle":"4px base unit scale: space-1 through space-16","name":"Spacing Tokens"},{"path":"preview/type-body.html","group":"Type","viewport":"700x200","subtitle":"FuturaStd Book/Medium — tagline, body, price, caption","name":"Body Typography"},{"path":"preview/type-display.html","group":"Type","viewport":"700x440","subtitle":"FuturaStd Condensed — display recto + italic en movimiento (Nike-style)","name":"Display Typography"},{"path":"ui_kits/ecommerce/index.html","group":"UI Kit — Ecommerce","viewport":"1280x700","subtitle":"Full interactive ecommerce prototype — Home, Shop, Product Detail, Cart","name":"Ecommerce UI Kit"}],"templates":[],"hasThumbnailHtml":false,"globalCssPaths":["colors_and_type.css"],"tokens":[{"name":"--color-yellow","value":"#FFD100","kind":"color","definedIn":"colors_and_type.css"},{"name":"--color-black","value":"#231F20","kind":"color","definedIn":"colors_and_type.css"},{"name":"--color-white","value":"#FFFFFF","kind":"color","definedIn":"colors_and_type.css"},{"name":"--color-brand-primary","value":"var(--color-yellow)","kind":"color","definedIn":"colors_and_type.css"},{"name":"--color-brand-dark","value":"var(--color-black)","kind":"color","definedIn":"colors_and_type.css"},{"name":"--color-brand-light","value":"var(--color-white)","kind":"color","definedIn":"colors_and_type.css"},{"name":"--color-text-primary","value":"var(--color-black)","kind":"font","definedIn":"colors_and_type.css"},{"name":"--color-text-inverse","value":"var(--color-white)","kind":"font","definedIn":"colors_and_type.css"},{"name":"--color-text-accent","value":"var(--color-yellow)","kind":"font","definedIn":"colors_and_type.css"},{"name":"--color-bg-light","value":"var(--color-white)","kind":"color","definedIn":"colors_and_type.css"},{"name":"--color-bg-dark","value":"var(--color-black)","kind":"color","definedIn":"colors_and_type.css"},{"name":"--color-bg-accent","value":"var(--color-yellow)","kind":"color","definedIn":"colors_and_type.css"},{"name":"--color-btn-primary-bg","value":"var(--color-yellow)","kind":"color","definedIn":"colors_and_type.css"},{"name":"--color-btn-primary-text","value":"var(--color-black)","kind":"font","definedIn":"colors_and_type.css"},{"name":"--color-btn-primary-hover-bg","value":"#e6bb00","kind":"color","definedIn":"colors_and_type.css"},{"name":"--color-btn-dark-bg","value":"var(--color-black)","kind":"color","definedIn":"colors_and_type.css"},{"name":"--color-btn-dark-text","value":"var(--color-white)","kind":"font","definedIn":"colors_and_type.css"},{"name":"--color-btn-dark-hover-bg","value":"#3a3536","kind":"color","definedIn":"colors_and_type.css"},{"name":"--color-border","value":"var(--color-black)","kind":"color","definedIn":"colors_and_type.css"},{"name":"--color-overlay","value":"rgba(35, 31, 32, 0.65)","kind":"color","definedIn":"colors_and_type.css"},{"name":"--accent-lime","value":"#C4FF1F","kind":"color","definedIn":"colors_and_type.css"},{"name":"--accent-violet","value":"#7C3AED","kind":"color","definedIn":"colors_and_type.css"},{"name":"--accent-coral","value":"#FF5A1F","kind":"color","definedIn":"colors_and_type.css"},{"name":"--accent-magenta","value":"#FF1F6B","kind":"color","definedIn":"colors_and_type.css"},{"name":"--accent-forest","value":"#1F6F54","kind":"color","definedIn":"colors_and_type.css"},{"name":"--accent-sky","value":"#2E7CC2","kind":"color","definedIn":"colors_and_type.css"},{"name":"--accent-clay","value":"#C2570C","kind":"color","definedIn":"colors_and_type.css"},{"name":"--accent-sand","value":"#E9E2D0","kind":"color","definedIn":"colors_and_type.css"},{"name":"--font-display","value":"\"FuturaStdCondensed\", \"Barlow Condensed\", sans-serif","kind":"font","definedIn":"colors_and_type.css"},{"name":"--font-body","value":"\"FuturaStd\", \"Futura\", sans-serif","kind":"font","definedIn":"colors_and_type.css"},{"name":"--text-xs","value":"12px","kind":"font","definedIn":"colors_and_type.css"},{"name":"--text-sm","value":"14px","kind":"font","definedIn":"colors_and_type.css"},{"name":"--text-base","value":"16px","kind":"font","definedIn":"colors_and_type.css"},{"name":"--text-md","value":"18px","kind":"font","definedIn":"colors_and_type.css"},{"name":"--text-lg","value":"22px","kind":"font","definedIn":"colors_and_type.css"},{"name":"--text-xl","value":"28px","kind":"font","definedIn":"colors_and_type.css"},{"name":"--text-2xl","value":"36px","kind":"font","definedIn":"colors_and_type.css"},{"name":"--text-3xl","value":"48px","kind":"font","definedIn":"colors_and_type.css"},{"name":"--text-4xl","value":"64px","kind":"font","definedIn":"colors_and_type.css"},{"name":"--text-5xl","value":"88px","kind":"font","definedIn":"colors_and_type.css"},{"name":"--text-6xl","value":"120px","kind":"font","definedIn":"colors_and_type.css"},{"name":"--leading-tight","value":"0.9","kind":"font","definedIn":"colors_and_type.css"},{"name":"--leading-snug","value":"1.0","kind":"font","definedIn":"colors_and_type.css"},{"name":"--leading-normal","value":"1.2","kind":"font","definedIn":"colors_and_type.css"},{"name":"--leading-relaxed","value":"1.5","kind":"font","definedIn":"colors_and_type.css"},{"name":"--leading-loose","value":"1.7","kind":"font","definedIn":"colors_and_type.css"},{"name":"--tracking-tight","value":"-0.02em","kind":"font","definedIn":"colors_and_type.css"},{"name":"--tracking-normal","value":"0em","kind":"font","definedIn":"colors_and_type.css"},{"name":"--tracking-wide","value":"0.12em","kind":"font","definedIn":"colors_and_type.css"},{"name":"--tracking-wider","value":"0.2em","kind":"font","definedIn":"colors_and_type.css"},{"name":"--tracking-widest","value":"0.35em","kind":"font","definedIn":"colors_and_type.css"},{"name":"--space-1","value":"4px","kind":"spacing","definedIn":"colors_and_type.css"},{"name":"--space-2","value":"8px","kind":"spacing","definedIn":"colors_and_type.css"},{"name":"--space-3","value":"12px","kind":"spacing","definedIn":"colors_and_type.css"},{"name":"--space-4","value":"16px","kind":"spacing","definedIn":"colors_and_type.css"},{"name":"--space-5","value":"20px","kind":"spacing","definedIn":"colors_and_type.css"},{"name":"--space-6","value":"24px","kind":"spacing","definedIn":"colors_and_type.css"},{"name":"--space-8","value":"32px","kind":"spacing","definedIn":"colors_and_type.css"},{"name":"--space-10","value":"40px","kind":"spacing","definedIn":"colors_and_type.css"},{"name":"--space-12","value":"48px","kind":"spacing","definedIn":"colors_and_type.css"},{"name":"--space-16","value":"64px","kind":"spacing","definedIn":"colors_and_type.css"},{"name":"--space-20","value":"80px","kind":"spacing","definedIn":"colors_and_type.css"},{"name":"--space-24","value":"96px","kind":"spacing","definedIn":"colors_and_type.css"},{"name":"--space-32","value":"128px","kind":"spacing","definedIn":"colors_and_type.css"},{"name":"--radius-none","value":"0px","kind":"radius","definedIn":"colors_and_type.css"},{"name":"--radius-sm","value":"2px","kind":"radius","definedIn":"colors_and_type.css"},{"name":"--radius-md","value":"4px","kind":"radius","definedIn":"colors_and_type.css"},{"name":"--radius-lg","value":"8px","kind":"radius","definedIn":"colors_and_type.css"},{"name":"--radius-pill","value":"999px","kind":"radius","definedIn":"colors_and_type.css"},{"name":"--shadow-sm","value":"2px 2px 0px var(--color-black)","kind":"shadow","definedIn":"colors_and_type.css"},{"name":"--shadow-md","value":"4px 4px 0px var(--color-black)","kind":"shadow","definedIn":"colors_and_type.css"},{"name":"--shadow-lg","value":"6px 6px 0px var(--color-black)","kind":"shadow","definedIn":"colors_and_type.css"},{"name":"--shadow-xl","value":"8px 8px 0px var(--color-black)","kind":"shadow","definedIn":"colors_and_type.css"}],"themes":[],"fonts":[{"family":"FuturaStd","weight":"400","style":"normal","cssPath":"colors_and_type.css","files":["fonts/FuturaStd-Book.otf"]},{"family":"FuturaStd","weight":"500","style":"normal","cssPath":"colors_and_type.css","files":["fonts/FuturaStd-Medium.otf"]},{"family":"FuturaStd","weight":"700","style":"normal","cssPath":"colors_and_type.css","files":["fonts/FuturaStd-Bold.otf"]},{"family":"FuturaStd","weight":"800","style":"normal","cssPath":"colors_and_type.css","files":["fonts/FuturaStd-Heavy.otf"]},{"family":"FuturaStd","weight":"900","style":"normal","cssPath":"colors_and_type.css","files":["fonts/FuturaStd-ExtraBold.otf"]},{"family":"FuturaStdCondensed","weight":"300","style":"normal","cssPath":"colors_and_type.css","files":["fonts/FuturaStd-CondensedLight.otf"]},{"family":"FuturaStdCondensed","weight":"400","style":"normal","cssPath":"colors_and_type.css","files":["fonts/FuturaStd-Condensed.otf"]},{"family":"FuturaStdCondensed","weight":"700","style":"normal","cssPath":"colors_and_type.css","files":["fonts/FuturaStd-CondensedBold.otf"]},{"family":"FuturaStdCondensed","weight":"900","style":"normal","cssPath":"colors_and_type.css","files":["fonts/FuturaStd-CondensedExtraBd.otf"]}],"brandFonts":[{"family":"FuturaStd","status":"ok","tokens":["--font-body"],"path":"colors_and_type.css"},{"family":"FuturaStdCondensed","status":"ok","tokens":["--font-display"],"path":"colors_and_type.css"}],"source":"spa"}